RSIC_CPU/sc-cpu/alu.v
module alu(opA, opB, aluop, result, zero);
parameter width=32;
input [1:0] aluop; input [width-1:0] opA, opB;
output reg [width-1:0] result; output reg zero;         
always @(*) zero = (result == 0);                          
always @(opA, opB, aluop) begin
case (aluop) 0: result = opA + opB; 1: result = opA - opB;
2: result = opA & opB; 3: result = opA | opB;
default: result = 0;
endcase
end
endmodule

RSIC_CPU/sc-cpu/alu_tb.v
module alu_tb;
parameter width=32;
reg [width-1:0] opA, opB;
reg [1:0] aluop;
wire [width-1:0] result;
wire zero;

initial
begin
	opA = 0;
	opB = 0;
	aluop = 0;
	#1 opA = 100;
	opB = 200;
	#1 aluop = 1;
	#1 opA = 32'hFFFFFFF;
        opB = 32'h01234567;
        aluop = 2;
        #1 aluop = 3;
	#1 opB = 32'hFFFFFFFF;
	#1 aluop = 1;
	#1 opB = 32'h01234567;
	#1 aluop = 0;
	#1 opA = 32'h01234567;
	aluop = 1;
	#1;
end
alu #(width) alu1(.opA(opA),.opB(opB),.aluop(aluop),.zero(zero),.result(result));
initial $monitor("At time %t, result = %d, zero = %d", $time, result, zero);
initial
begin
  $dumpfile("alu_tb.vcd");
  $dumpvars(0, alu_tb);
end

endmodule

RSIC_CPU/sc-cpu/alu_tb.vcd
$date
	Sun Apr 17 12:28:11 2022
$end
$version
	Icarus Verilog
$end
$timescale
	1s
$end
$scope module alu_tb $end
$var wire 1 ! zero $end
$var wire 32 " result [31:0] $end
$var reg 2 # aluop [1:0] $end
$var reg 32 $ opA [31:0] $end
$var reg 32 % opB [31:0] $end
$scope module alu1 $end
$var wire 2 & aluop [1:0] $end
$var wire 32 ' opA [31:0] $end
$var wire 32 ( opB [31:0] $end
$var wire 1 ! zero $end
$var reg 32 ) result [31:0] $end
$upscope $end
$upscope $end
$enddefinitions $end
#0
$dumpvars
b0 )
b0 (
b0 '
b0 &
b0 %
b0 $
b0 #
b0 "
1!
$end
#1
0!
b100101100 "
b100101100 )
b11001000 %
b11001000 (
b1100100 $
b1100100 '
#2
b11111111111111111111111110011100 "
b11111111111111111111111110011100 )
b1 #
b1 &
#3
b1001000110100010101100111 "
b1001000110100010101100111 )
b10 #
b10 &
b1001000110100010101100111 %
b1001000110100010101100111 (
b1111111111111111111111111111 $
b1111111111111111111111111111 '
#4
b1111111111111111111111111111 "
b1111111111111111111111111111 )
b11 #
b11 &
#5
b11111111111111111111111111111111 "
b11111111111111111111111111111111 )
b11111111111111111111111111111111 %
b11111111111111111111111111111111 (
#6
b10000000000000000000000000000 "
b10000000000000000000000000000 )
b1 #
b1 &
#7
b1110110111001011101010011000 "
b1110110111001011101010011000 )
b1001000110100010101100111 %
b1001000110100010101100111 (
#8
b10001001000110100010101100110 "
b10001001000110100010101100110 )
b0 #
b0 &
#9
1!
b0 "
b0 )
b1 #
b1 &
b1001000110100010101100111 $
b1001000110100010101100111 '
